{
  "generatedAt": "2026-05-14T11:28:19.912769+02:00",
  "lastScan": {
    "id": "2026-05-14T11-27-14",
    "timestamp": "2026-05-14T11:27:14.595078+02:00",
    "durationFormatted": "1m 4s",
    "success": true,
    "failureReason": null,
    "newOffers": 14,
    "activeOffers": 319,
    "foundOffers": 434
  },
  "recentScans": [
    {
      "id": "2026-05-14T11-27-14",
      "timestamp": "2026-05-14T11:27:14.595078+02:00",
      "durationFormatted": "1m 4s",
      "success": true,
      "failureReason": null,
      "newOffers": 14,
      "activeOffers": 319,
      "foundOffers": 434
    },
    {
      "id": "2026-05-14T09-44-08",
      "timestamp": "2026-05-14T09:44:08.667314+02:00",
      "durationFormatted": "2m 4s",
      "success": true,
      "failureReason": null,
      "newOffers": 8,
      "activeOffers": 307,
      "foundOffers": 436
    },
    {
      "id": "2026-05-14T09-02-58",
      "timestamp": "2026-05-14T09:02:58.336708+02:00",
      "durationFormatted": "2m 50s",
      "success": true,
      "failureReason": null,
      "newOffers": 24,
      "activeOffers": 299,
      "foundOffers": 438
    }
  ],
  "nextScanAt": "2026-05-14T15:00:00+02:00"
}