{
  "generatedAt": "2026-07-07T17:40:39.686447+02:00",
  "lastScan": {
    "id": "2026-07-07T17-39-46",
    "timestamp": "2026-07-07T17:39:46.001697+02:00",
    "durationFormatted": "52s",
    "success": true,
    "failureReason": null,
    "newOffers": 7,
    "deactivatedOffers": 11,
    "activeOffers": 610,
    "foundOffers": 702
  },
  "recentScans": [
    {
      "id": "2026-07-07T17-39-46",
      "timestamp": "2026-07-07T17:39:46.001697+02:00",
      "durationFormatted": "52s",
      "success": true,
      "failureReason": null,
      "newOffers": 7,
      "deactivatedOffers": 11,
      "activeOffers": 610,
      "foundOffers": 702
    },
    {
      "id": "2026-07-07T12-18-37",
      "timestamp": "2026-07-07T12:18:37.606186+02:00",
      "durationFormatted": "48s",
      "success": true,
      "failureReason": null,
      "newOffers": 7,
      "deactivatedOffers": 7,
      "activeOffers": 609,
      "foundOffers": 708
    },
    {
      "id": "2026-07-06T22-46-03",
      "timestamp": "2026-07-06T22:46:03.230544+02:00",
      "durationFormatted": "51s",
      "success": true,
      "failureReason": null,
      "newOffers": 5,
      "deactivatedOffers": 7,
      "activeOffers": 603,
      "foundOffers": 704
    }
  ],
  "nextScanAt": "2026-07-07T21:00:00+02:00"
}