{
  "system": "sonar",
  "version": "1.0.0",
  "generatedAt": "2026-05-13T19:54:06.164538+02:00",
  "status": {
    "current": "operational",
    "isHealthy": true,
    "hasErrors": false,
    "errorMessages": []
  },
  "lastScan": {
    "id": "2026-05-13T19-53-14",
    "timestamp": "2026-05-13T19:53:14.190278+02:00",
    "endTimestamp": "2026-05-13T19:54:05.526362+02:00",
    "durationSeconds": 51.34,
    "durationFormatted": "51s",
    "uiStatus": "success",
    "rawStatus": "completed",
    "offers": {
      "found": 431,
      "processed": 184,
      "new": 0,
      "updated": 184,
      "active": 221,
      "inactive": 203
    },
    "skipped": {
      "noAddress": 135,
      "noCoords": 90,
      "duplicates": 21
    },
    "errors": [],
    "hasErrors": false
  },
  "schedule": {
    "times": [
      "09:00",
      "15:00",
      "21:00"
    ],
    "timezone": "Europe/Warsaw",
    "nextScanAt": "2026-05-13T21:00:00+02:00"
  },
  "statistics": {
    "totalScans": 100,
    "successRate": 98.0,
    "avgDurationSeconds": 326.8,
    "avgOffersFound": 404.6
  }
}