{
  "system": "sonar",
  "version": "1.0.0",
  "generatedAt": "2026-06-08T13:49:43.163516+02:00",
  "status": {
    "current": "operational",
    "isHealthy": true,
    "hasErrors": false,
    "errorMessages": []
  },
  "lastScan": {
    "id": "2026-06-08T13-49-00",
    "timestamp": "2026-06-08T13:49:00.157751+02:00",
    "endTimestamp": "2026-06-08T13:49:42.201775+02:00",
    "durationSeconds": 42.04,
    "durationFormatted": "42s",
    "uiStatus": "success",
    "rawStatus": "completed",
    "offers": {
      "found": 495,
      "processed": 436,
      "new": 0,
      "deactivated": null,
      "updated": 436,
      "active": 411,
      "inactive": 405
    },
    "skipped": {
      "noAddress": 30,
      "noPrice": 0,
      "noCoords": 15,
      "duplicates": 4
    },
    "errors": [],
    "hasErrors": false
  },
  "schedule": {
    "times": [
      "09:00",
      "15:00",
      "21:00"
    ],
    "timezone": "Europe/Warsaw",
    "nextScanAt": "2026-06-08T15:00:00+02:00"
  },
  "statistics": {
    "totalScans": 100,
    "successRate": 97.0,
    "avgDurationSeconds": 42.23,
    "avgOffersFound": 370.1
  }
}