{
  "system": "sonar",
  "version": "1.0.0",
  "generatedAt": "2026-05-01T22:05:49.512215+02:00",
  "status": {
    "current": "operational",
    "isHealthy": true,
    "hasErrors": false,
    "errorMessages": []
  },
  "lastScan": {
    "id": "2026-05-01T22-00-25",
    "timestamp": "2026-05-01T22:00:25.930969+02:00",
    "endTimestamp": "2026-05-01T22:05:49.001234+02:00",
    "durationSeconds": 323.07,
    "durationFormatted": "5m 23s",
    "uiStatus": "success",
    "rawStatus": "completed",
    "offers": {
      "found": 407,
      "processed": 84,
      "new": 0,
      "updated": 84,
      "active": 106,
      "inactive": 169
    },
    "skipped": {
      "noAddress": 164,
      "noCoords": 153,
      "duplicates": 6
    },
    "errors": [],
    "hasErrors": false
  },
  "schedule": {
    "times": [
      "09:00",
      "15:00",
      "21:00"
    ],
    "timezone": "Europe/Warsaw",
    "nextScanAt": "2026-05-02T09:00:00+02:00"
  },
  "statistics": {
    "totalScans": 100,
    "successRate": 100.0,
    "avgDurationSeconds": 347.72,
    "avgOffersFound": 403.1
  }
}