{
  "generated_at": "2026-05-29T12:39:07.911204+02:00",
  "total_offers": 766,
  "offers_with_change": 89,
  "date_range": {
    "min": "2026-02-28T20:46:40.989752+01:00",
    "max": "2026-05-29T12:39:00.125261+02:00"
  },
  "entries": [
    {
      "id": "dwa-pokoje-do-wynajecia-CID3-ID19kUsi",
      "url": "https://www.olx.pl/d/oferta/dwa-pokoje-do-wynajecia-CID3-ID19kUsi.html?search_reason=search%7Corganic",
      "address": "Wyczółkowskiego 1M",
      "first_price": 2000,
      "current_price": 1000,
      "total_diff_pln": -1000,
      "total_diff_pct": -50.0,
      "trend": "down",
      "first_seen": "2026-03-01T11:26:07.465277+01:00",
      "last_seen": "2026-05-29T12:39:00.125261+02:00",
      "active": true,
      "num_changes": 2,
      "has_coords": true,
      "timeline": [
        {
          "date": "2026-03-01T11:26:07.465277+01:00",
          "price": 2000,
          "approximated": false
        },
        {
          "date": "2026-03-01T15:58:00.861774+01:00",
          "price": 1000,
          "approximated": false
        }
      ]
    },
    {
      "id": "pokoje-10m2-15m2-super-lokalizacja-wynajem-lublin-srodmiescie-ul-gliniana-CID3-ID16sgfg",
      "url": "https://www.olx.pl/d/oferta/pokoje-10m2-15m2-super-lokalizacja-wynajem-lublin-srodmiescie-ul-gliniana-CID3-ID16sgfg.html?search_reason=search%7Corganic",
      "address": "Gliniana",
      "first_price": 1100,
      "current_price": 700,
      "total_diff_pln": -400,
      "total_diff_pct": -36.36,
      "trend": "down",
      "first_seen": "2026-05-14T11:27:51.110311+02:00",
      "last_seen": "2026-05-29T12:39:00.125261+02:00",
      "active": true,
      "num_changes": 2,
      "has_coords": true,
      "timeline": [
        {
          "date": "2026-05-14T11:27:51.110311+02:00",
          "price": 1100,
          "approximated": false
        },
        {
          "date": "2026-05-22T13:02:02.498710+02:00",
          "price": 700,
          "approximated": false
        }
      ]
    },
    {
      "id": "pokoj-z-balkonem-i-widokiem-na-ratusz-scisle-centrum-CID3-ID19ClP1",
      "url": "https://www.olx.pl/d/oferta/pokoj-z-balkonem-i-widokiem-na-ratusz-scisle-centrum-CID3-ID19ClP1.html?search_reason=search%7Corganic",
      "address": "Świętoduska 12",
      "first_price": 1300,
      "current_price": 990,
      "total_diff_pln": -310,
      "total_diff_pct": -23.85,
      "trend": "down",
      "first_seen": "2026-03-03T11:10:05.050475+01:00",
      "last_seen": "2026-03-31T10:55:03.208355+02:00",
      "active": false,
      "num_changes": 5,
      "has_coords": true,
      "timeline": [
        {
          "date": "2026-03-03T11:10:05.050475+01:00",
          "price": 1300,
          "approximated": false
        },
        {
          "date": "2026-03-07T12:19:13.764465+01:00",
          "price": 1190,
          "approximated": true
        },
        {
          "date": "2026-03-11T13:28:22.478455+01:00",
          "price": 1090,
          "approximated": true
        },
        {
          "date": "2026-03-15T14:37:31.192445+01:00",
          "price": 1020,
          "approximated": true
        },
        {
          "date": "2026-03-19T15:46:39.906435+01:00",
          "price": 990,
          "approximated": false
        }
      ]
    },
    {
      "id": "pokoj-do-wynajecia-CID3-ID19tApV",
      "url": "https://www.olx.pl/d/oferta/pokoj-do-wynajecia-CID3-ID19tApV.html?search_reason=search%7Corganic",
      "address": "Nowy Świat 5",
      "first_price": 1500,
      "current_price": 1200,
      "total_diff_pln": -300,
      "total_diff_pct": -20.0,
      "trend": "down",
      "first_seen": "2026-02-28T20:46:40.992421+01:00",
      "last_seen": "2026-03-22T09:31:15.316581+01:00",
      "active": false,
      "num_changes": 2,
      "has_coords": true,
      "timeline": [
        {
          "date": "2026-02-28T20:46:40.992421+01:00",
          "price": 1500,
          "approximated": false
        },
        {
          "date": "2026-03-01T15:58:00.861366+01:00",
          "price": 1200,
          "approximated": false
        }
      ]
    },
    {
      "id": "do-wynajecia-pokoje-w-lublinie-od-1-kwietnia-CID3-ID12BYdw",
      "url": "https://www.olx.pl/d/oferta/do-wynajecia-pokoje-w-lublinie-od-1-kwietnia-CID3-ID12BYdw.html?search_reason=search%7Corganic",
      "address": "Nowy Świat 5",
      "first_price": 1500,
      "current_price": 1200,
      "total_diff_pln": -300,
      "total_diff_pct": -20.0,
      "trend": "down",
      "first_seen": "2026-03-01T11:26:11.071811+01:00",
      "last_seen": "2026-03-20T09:37:56.323506+01:00",
      "active": false,
      "num_changes": 2,
      "has_coords": true,
      "timeline": [
        {
          "date": "2026-03-01T11:26:11.071811+01:00",
          "price": 1500,
          "approximated": false
        },
        {
          "date": "2026-03-01T15:58:00.861960+01:00",
          "price": 1200,
          "approximated": false
        }
      ]
    },
    {
      "id": "pokoj-mieszkanie-blisko-medyczna-kul-umcs-ul-braci-wieniawskich-4-CID3-ID17Guld",
      "url": "https://www.olx.pl/d/oferta/pokoj-mieszkanie-blisko-medyczna-kul-umcs-ul-braci-wieniawskich-4-CID3-ID17Guld.html?search_reason=search%7Corganic",
      "address": "Braci Wieniawskich 4",
      "first_price": 1500,
      "current_price": 1200,
      "total_diff_pln": -300,
      "total_diff_pct": -20.0,
      "trend": "down",
      "first_seen": "2026-03-14T15:26:37.109568+01:00",
      "last_seen": "2026-05-16T21:57:37.429686+02:00",
      "active": false,
      "num_changes": 2,
      "has_coords": true,
      "timeline": [
        {
          "date": "2026-03-14T15:26:37.109568+01:00",
          "price": 1500,
          "approximated": false
        },
        {
          "date": "2026-03-20T21:29:04.120565+01:00",
          "price": 1200,
          "approximated": false
        }
      ]
    },
    {
      "id": "pokoj-jednoosobowy-z-balkonem-na-czechowie-dolnym-od-zaraz-CID3-IDPIYbN",
      "url": "https://www.olx.pl/d/oferta/pokoj-jednoosobowy-z-balkonem-na-czechowie-dolnym-od-zaraz-CID3-IDPIYbN.html?search_reason=search%7Corganic",
      "address": "Kameralna 5",
      "first_price": 865,
      "current_price": 590,
      "total_diff_pln": -275,
      "total_diff_pct": -31.79,
      "trend": "down",
      "first_seen": "2026-02-28T20:46:43.306356+01:00",
      "last_seen": "2026-05-23T22:01:58.707168+02:00",
      "active": false,
      "num_changes": 3,
      "has_coords": true,
      "timeline": [
        {
          "date": "2026-02-28T20:46:43.306356+01:00",
          "price": 865,
          "approximated": false
        },
        {
          "date": "2026-03-25T06:13:39.787211+01:00",
          "price": 790,
          "approximated": true
        },
        {
          "date": "2026-04-18T16:40:36.268067+02:00",
          "price": 590,
          "approximated": false
        }
      ]
    },
    {
      "id": "pokoj-do-wynajecia-na-czechowie-jana-kiepury-CID3-ID17bGrP",
      "url": "https://www.olx.pl/d/oferta/pokoj-do-wynajecia-na-czechowie-jana-kiepury-CID3-ID17bGrP.html?search_reason=search%7Corganic",
      "address": "Jana Kiepury 11",
      "first_price": 950,
      "current_price": 700,
      "total_diff_pln": -250,
      "total_diff_pct": -26.32,
      "trend": "down",
      "first_seen": "2026-03-17T21:36:24.612982+01:00",
      "last_seen": "2026-05-28T18:47:12.352850+02:00",
      "active": false,
      "num_changes": 2,
      "has_coords": true,
      "timeline": [
        {
          "date": "2026-03-17T21:36:24.612982+01:00",
          "price": 950,
          "approximated": false
        },
        {
          "date": "2026-04-28T22:13:50.815400+02:00",
          "price": 700,
          "approximated": false
        }
      ]
    },
    {
      "id": "komfortowy-pokoj-z-klimatyzacja-dla-1-lub-2-osob-wolny-od-zaraz-CID3-ID16WJZ7",
      "url": "https://www.olx.pl/d/oferta/komfortowy-pokoj-z-klimatyzacja-dla-1-lub-2-osob-wolny-od-zaraz-CID3-ID16WJZ7.html?search_reason=search%7Corganic",
      "address": "Koralowa 9",
      "first_price": 1400,
      "current_price": 1150,
      "total_diff_pln": -250,
      "total_diff_pct": -17.86,
      "trend": "down",
      "first_seen": "2026-03-22T15:25:58.546336+01:00",
      "last_seen": "2026-05-23T22:01:58.707168+02:00",
      "active": false,
      "num_changes": 2,
      "has_coords": true,
      "timeline": [
        {
          "date": "2026-03-22T15:25:58.546336+01:00",
          "price": 1400,
          "approximated": false
        },
        {
          "date": "2026-03-26T16:02:33.130252+01:00",
          "price": 1150,
          "approximated": false
        }
      ]
    },
    {
      "id": "pokoj-w-2-pokojowym-centrum-saski-parking-w-cenie-CID3-ID1a8m8n",
      "url": "https://www.olx.pl/d/oferta/pokoj-w-2-pokojowym-centrum-saski-parking-w-cenie-CID3-ID1a8m8n.html?search_reason=search%7Cpromoted",
      "address": "Boczna Lubomelskiej",
      "first_price": 1450,
      "current_price": 1200,
      "total_diff_pln": -250,
      "total_diff_pct": -17.24,
      "trend": "down",
      "first_seen": "2026-05-25T22:19:54.203906+02:00",
      "last_seen": "2026-05-29T12:39:00.125261+02:00",
      "active": true,
      "num_changes": 2,
      "has_coords": true,
      "timeline": [
        {
          "date": "2026-05-25T22:19:54.203895+02:00",
          "price": 1450,
          "approximated": false
        },
        {
          "date": "2026-05-26T14:49:29.846969+02:00",
          "price": 1200,
          "approximated": false
        }
      ]
    },
    {
      "id": "pokoj-dla-studentki-mieszkanie-stancja-do-wynajecia-CID3-ID150hp7",
      "url": "https://www.olx.pl/d/oferta/pokoj-dla-studentki-mieszkanie-stancja-do-wynajecia-CID3-ID150hp7.html?search_reason=search%7Corganic",
      "address": "Niepodległości 10",
      "first_price": 800,
      "current_price": 600,
      "total_diff_pln": -200,
      "total_diff_pct": -25.0,
      "trend": "down",
      "first_seen": "2026-02-28T20:46:42.764004+01:00",
      "last_seen": "2026-05-29T12:39:00.125261+02:00",
      "active": true,
      "num_changes": 2,
      "has_coords": true,
      "timeline": [
        {
          "date": "2026-02-28T20:46:42.764004+01:00",
          "price": 800,
          "approximated": false
        },
        {
          "date": "2026-05-21T20:55:44.568538+02:00",
          "price": 600,
          "approximated": false
        }
      ]
    },
    {
      "id": "pokoj-8m2-czechow-ul-wojciecha-zywnego-5-blisko-wincentego-pola-CID3-ID179Ozw",
      "url": "https://www.olx.pl/d/oferta/pokoj-8m2-czechow-ul-wojciecha-zywnego-5-blisko-wincentego-pola-CID3-ID179Ozw.html?search_reason=search%7Corganic",
      "address": "Wojciecha Żywnego 5",
      "first_price": 800,
      "current_price": 600,
      "total_diff_pln": -200,
      "total_diff_pct": -25.0,
      "trend": "down",
      "first_seen": "2026-03-01T11:33:26.587912+01:00",
      "last_seen": "2026-05-12T11:33:13.205930+02:00",
      "active": false,
      "num_changes": 3,
      "has_coords": true,
      "timeline": [
        {
          "date": "2026-03-01T11:33:26.587912+01:00",
          "price": 800,
          "approximated": false
        },
        {
          "date": "2026-03-05T14:54:48.106414+01:00",
          "price": 700,
          "approximated": true
        },
        {
          "date": "2026-03-09T18:16:09.624915+01:00",
          "price": 600,
          "approximated": false
        }
      ]
    },
    {
      "id": "pokoj-do-wynajecia-ulmlodej-polski-blisko-um-wincentego-pola-i-wspia-CID3-IDL3pTw",
      "url": "https://www.olx.pl/d/oferta/pokoj-do-wynajecia-ulmlodej-polski-blisko-um-wincentego-pola-i-wspia-CID3-IDL3pTw.html?search_reason=search%7Cpromoted",
      "address": "Młodej Polski 32C",
      "first_price": 999,
      "current_price": 799,
      "total_diff_pln": -200,
      "total_diff_pct": -20.02,
      "trend": "down",
      "first_seen": "2026-03-14T15:26:36.486212+01:00",
      "last_seen": "2026-05-28T12:45:32.500493+02:00",
      "active": false,
      "num_changes": 2,
      "has_coords": true,
      "timeline": [
        {
          "date": "2026-03-14T15:26:36.486212+01:00",
          "price": 999,
          "approximated": false
        },
        {
          "date": "2026-03-21T09:28:24.866230+01:00",
          "price": 799,
          "approximated": false
        }
      ]
    },
    {
      "id": "ladny-pokoj-w-nowy-mieszkaniu-czynsz-najmu-1300-zl-m-c-CID3-IDW07tZ",
      "url": "https://www.olx.pl/d/oferta/ladny-pokoj-w-nowy-mieszkaniu-czynsz-najmu-1300-zl-m-c-CID3-IDW07tZ.html?search_reason=search%7Cpromoted",
      "address": "Leszczyńskiego 25",
      "first_price": 1300,
      "current_price": 1100,
      "total_diff_pln": -200,
      "total_diff_pct": -15.38,
      "trend": "down",
      "first_seen": "2026-03-17T21:36:25.360756+01:00",
      "last_seen": "2026-05-19T18:14:20.304116+02:00",
      "active": false,
      "num_changes": 2,
      "has_coords": true,
      "timeline": [
        {
          "date": "2026-03-17T21:36:25.360756+01:00",
          "price": 1300,
          "approximated": false
        },
        {
          "date": "2026-05-14T08:52:26.611690+02:00",
          "price": 1100,
          "approximated": false
        }
      ]
    },
    {
      "id": "wynajme-pokoj-2-osobowy-z-balkonem-kalinowszczyzna-ul-kustronia-2-CID3-ID19GF7W",
      "url": "https://www.olx.pl/d/oferta/wynajme-pokoj-2-osobowy-z-balkonem-kalinowszczyzna-ul-kustronia-2-CID3-ID19GF7W.html?search_reason=search%7Cpromoted",
      "address": "Kustronia 2",
      "first_price": 1200,
      "current_price": 1000,
      "total_diff_pln": -200,
      "total_diff_pct": -16.67,
      "trend": "down",
      "first_seen": "2026-04-11T22:28:48.873863+02:00",
      "last_seen": "2026-05-08T16:35:31.251405+02:00",
      "active": false,
      "num_changes": 2,
      "has_coords": true,
      "timeline": [
        {
          "date": "2026-04-11T22:28:48.873863+02:00",
          "price": 1200,
          "approximated": false
        },
        {
          "date": "2026-05-06T22:21:31.166856+02:00",
          "price": 1000,
          "approximated": false
        }
      ]
    },
    {
      "id": "duzy-pokoj-do-wynajecia-od-zaraz-miasteczko-akademickie-CID3-ID18wwTB",
      "url": "https://www.olx.pl/d/oferta/duzy-pokoj-do-wynajecia-od-zaraz-miasteczko-akademickie-CID3-ID18wwTB.html?search_reason=search%7Cpromoted",
      "address": "Langiewicza 3A",
      "first_price": 900,
      "current_price": 700,
      "total_diff_pln": -200,
      "total_diff_pct": -22.22,
      "trend": "down",
      "first_seen": "2026-04-13T17:14:48.456544+02:00",
      "last_seen": "2026-05-13T11:36:22.747653+02:00",
      "active": false,
      "num_changes": 3,
      "has_coords": true,
      "timeline": [
        {
          "date": "2026-04-13T17:14:48.456544+02:00",
          "price": 900,
          "approximated": false
        },
        {
          "date": "2026-04-18T04:54:36.706339+02:00",
          "price": 800,
          "approximated": true
        },
        {
          "date": "2026-04-22T16:34:24.956134+02:00",
          "price": 700,
          "approximated": false
        }
      ]
    },
    {
      "id": "pokoj-z-balkonem-do-wynajecia-od-zaraz-CID3-ID1ac9Lm",
      "url": "https://www.olx.pl/d/oferta/pokoj-z-balkonem-do-wynajecia-od-zaraz-CID3-ID1ac9Lm.html?search_reason=search%7Corganic",
      "address": "Leszetyckiego 5",
      "first_price": 900,
      "current_price": 700,
      "total_diff_pln": -200,
      "total_diff_pct": -22.22,
      "trend": "down",
      "first_seen": "2026-04-13T17:14:50.326448+02:00",
      "last_seen": "2026-05-13T11:36:22.747653+02:00",
      "active": false,
      "num_changes": 2,
      "has_coords": true,
      "timeline": [
        {
          "date": "2026-04-13T17:14:50.326448+02:00",
          "price": 900,
          "approximated": false
        },
        {
          "date": "2026-04-16T11:14:56.693363+02:00",
          "price": 700,
          "approximated": false
        }
      ]
    },
    {
      "id": "wymajme-pokoj-z-balkonem-od-1-lipca-1-wrzesnia-ul-leszka-czarnego-lsm-zmywarka-suszarka-standar-ikea-CID3-ID1azSIP",
      "url": "https://www.olx.pl/d/oferta/wymajme-pokoj-z-balkonem-od-1-lipca-1-wrzesnia-ul-leszka-czarnego-lsm-zmywarka-suszarka-standar-ikea-CID3-ID1azSIP.html?search_reason=search%7Corganic",
      "address": "Leszka Czarnego",
      "first_price": 1500,
      "current_price": 1300,
      "total_diff_pln": -200,
      "total_diff_pct": -13.33,
      "trend": "down",
      "first_seen": "2026-05-14T09:44:51.499757+02:00",
      "last_seen": "2026-05-29T12:39:00.120205+02:00",
      "active": true,
      "num_changes": 2,
      "has_coords": true,
      "timeline": [
        {
          "date": "2026-05-14T09:44:51.499757+02:00",
          "price": 1500,
          "approximated": false
        },
        {
          "date": "2026-05-29T12:39:00.120205+02:00",
          "price": 1300,
          "approximated": false
        }
      ]
    },
    {
      "id": "pokoj-w-3-osobowym-mieszkaniu-CID3-ID1aN2hC",
      "url": "https://www.olx.pl/d/oferta/pokoj-w-3-osobowym-mieszkaniu-CID3-ID1aN2hC.html?search_reason=search%7Corganic",
      "address": "Szczytowa",
      "first_price": 1000,
      "current_price": 800,
      "total_diff_pln": -200,
      "total_diff_pct": -20.0,
      "trend": "down",
      "first_seen": "2026-05-24T11:14:20.515901+02:00",
      "last_seen": "2026-05-29T12:39:00.125261+02:00",
      "active": true,
      "num_changes": 2,
      "has_coords": true,
      "timeline": [
        {
          "date": "2026-05-24T11:14:20.515878+02:00",
          "price": 1000,
          "approximated": false
        },
        {
          "date": "2026-05-25T12:53:51.010404+02:00",
          "price": 800,
          "approximated": false
        }
      ]
    },
    {
      "id": "przytulny-pokoj-jednoosobowy-blisko-uczelni-CID3-ID19OLvV",
      "url": "https://www.olx.pl/d/oferta/przytulny-pokoj-jednoosobowy-blisko-uczelni-CID3-ID19OLvV.html?search_reason=search%7Corganic",
      "address": "Kaliska 1D",
      "first_price": 780,
      "current_price": 600,
      "total_diff_pln": -180,
      "total_diff_pct": -23.08,
      "trend": "down",
      "first_seen": "2026-03-16T21:35:38.072055+01:00",
      "last_seen": "2026-05-23T22:01:58.707168+02:00",
      "active": false,
      "num_changes": 3,
      "has_coords": true,
      "timeline": [
        {
          "date": "2026-03-16T21:35:38.072055+01:00",
          "price": 780,
          "approximated": false
        },
        {
          "date": "2026-04-03T03:52:22.750032+01:00",
          "price": 650,
          "approximated": true
        },
        {
          "date": "2026-04-20T11:09:07.428009+02:00",
          "price": 600,
          "approximated": false
        }
      ]
    },
    {
      "id": "duzy-pokoj-wolny-od-zaraz-wysoki-standard-czechow-dolny-umcs-kul-up-CID3-ID1a6An5",
      "url": "https://www.olx.pl/d/oferta/duzy-pokoj-wolny-od-zaraz-wysoki-standard-czechow-dolny-umcs-kul-up-CID3-ID1a6An5.html?search_reason=search%7Corganic",
      "address": "Skołuby 10B",
      "first_price": 880,
      "current_price": 700,
      "total_diff_pln": -180,
      "total_diff_pct": -20.45,
      "trend": "down",
      "first_seen": "2026-04-07T17:05:56.035148+02:00",
      "last_seen": "2026-05-20T18:20:34.467261+02:00",
      "active": false,
      "num_changes": 3,
      "has_coords": true,
      "timeline": [
        {
          "date": "2026-04-07T17:05:56.035148+02:00",
          "price": 880,
          "approximated": false
        },
        {
          "date": "2026-04-22T02:13:09.411400+02:00",
          "price": 800,
          "approximated": true
        },
        {
          "date": "2026-05-06T11:20:22.787653+02:00",
          "price": 700,
          "approximated": false
        }
      ]
    },
    {
      "id": "wolny-pokoj-od-zaraz-na-czechowie-CID3-ID17aiNS",
      "url": "https://www.olx.pl/d/oferta/wolny-pokoj-od-zaraz-na-czechowie-CID3-ID17aiNS.html?search_reason=search%7Corganic",
      "address": "Paganiniego 12",
      "first_price": 850,
      "current_price": 700,
      "total_diff_pln": -150,
      "total_diff_pct": -17.65,
      "trend": "down",
      "first_seen": "2026-03-02T11:36:41.744853+01:00",
      "last_seen": "2026-05-28T18:47:12.352850+02:00",
      "active": false,
      "num_changes": 2,
      "has_coords": true,
      "timeline": [
        {
          "date": "2026-03-02T11:36:41.744853+01:00",
          "price": 850,
          "approximated": false
        },
        {
          "date": "2026-04-28T22:13:50.815589+02:00",
          "price": 700,
          "approximated": false
        }
      ]
    },
    {
      "id": "pokoj-na-wynajem-w-mieszkaniu-swiezo-po-remoncie-lsm-ulica-balladyny-CID3-ID1aAt73",
      "url": "https://www.olx.pl/d/oferta/pokoj-na-wynajem-w-mieszkaniu-swiezo-po-remoncie-lsm-ulica-balladyny-CID3-ID1aAt73.html?search_reason=search%7Corganic",
      "address": "Osiedle Słowackiego",
      "first_price": 1250,
      "current_price": 1100,
      "total_diff_pln": -150,
      "total_diff_pct": -12.0,
      "trend": "down",
      "first_seen": "2026-05-11T17:51:11.325919+02:00",
      "last_seen": "2026-05-29T12:39:00.125261+02:00",
      "active": true,
      "num_changes": 3,
      "has_coords": true,
      "timeline": [
        {
          "date": "2026-05-11T17:51:11.325919+02:00",
          "price": 1250,
          "approximated": false
        },
        {
          "date": "2026-05-14T07:54:24.375553+02:00",
          "price": 1150,
          "approximated": true
        },
        {
          "date": "2026-05-16T21:57:37.425188+02:00",
          "price": 1100,
          "approximated": false
        }
      ]
    },
    {
      "id": "jednoosobowy-pokoj-do-wynajecia-ul-zarnowiecka-3-CID3-ID17E20t",
      "url": "https://www.olx.pl/d/oferta/jednoosobowy-pokoj-do-wynajecia-ul-zarnowiecka-3-CID3-ID17E20t.html?search_reason=search%7Corganic",
      "address": "żarnowiecka 3",
      "first_price": 850,
      "current_price": 730,
      "total_diff_pln": -120,
      "total_diff_pct": -14.12,
      "trend": "down",
      "first_seen": "2026-03-02T11:36:52.151460+01:00",
      "last_seen": "2026-03-29T10:37:57.938861+02:00",
      "active": false,
      "num_changes": 3,
      "has_coords": true,
      "timeline": [
        {
          "date": "2026-03-02T11:36:52.151460+01:00",
          "price": 850,
          "approximated": false
        },
        {
          "date": "2026-03-14T16:35:40.993741+01:00",
          "price": 800,
          "approximated": true
        },
        {
          "date": "2026-03-26T21:34:29.836022+01:00",
          "price": 730,
          "approximated": false
        }
      ]
    },
    {
      "id": "pokoj-blisko-kul-umcs-1000m-ul-popieluszki-CID3-ID18VUIo",
      "url": "https://www.olx.pl/d/oferta/pokoj-blisko-kul-umcs-1000m-ul-popieluszki-CID3-ID18VUIo.html?search_reason=search%7Corganic",
      "address": "Popiełuszki 31",
      "first_price": 1000,
      "current_price": 890,
      "total_diff_pln": -110,
      "total_diff_pct": -11.0,
      "trend": "down",
      "first_seen": "2026-03-01T11:33:26.564596+01:00",
      "last_seen": "2026-03-10T22:07:17.754325+01:00",
      "active": false,
      "num_changes": 2,
      "has_coords": true,
      "timeline": [
        {
          "date": "2026-03-01T11:33:26.564596+01:00",
          "price": 1000,
          "approximated": false
        },
        {
          "date": "2026-03-01T15:58:00.861861+01:00",
          "price": 890,
          "approximated": false
        }
      ]
    },
    {
      "id": "pokoj-na-wynajem-400m-od-politechniki-CID3-ID19Jyuo",
      "url": "https://www.olx.pl/d/oferta/pokoj-na-wynajem-400m-od-politechniki-CID3-ID19Jyuo.html?search_reason=search%7Corganic",
      "address": "Siewnej 16",
      "first_price": 900,
      "current_price": 790,
      "total_diff_pln": -110,
      "total_diff_pct": -12.22,
      "trend": "down",
      "first_seen": "2026-03-11T11:12:07.544150+01:00",
      "last_seen": "2026-04-09T22:45:49.931004+02:00",
      "active": false,
      "num_changes": 3,
      "has_coords": true,
      "timeline": [
        {
          "date": "2026-03-11T11:12:07.544150+01:00",
          "price": 900,
          "approximated": false
        },
        {
          "date": "2026-03-19T01:37:20.336486+01:00",
          "price": 800,
          "approximated": true
        },
        {
          "date": "2026-03-26T16:02:33.128822+01:00",
          "price": 790,
          "approximated": false
        }
      ]
    },
    {
      "id": "pokoj-dwuosobowy-lublin-ul-paganiniego-czechow-blisko-um-kawalerka-CID3-ID19yGvY",
      "url": "https://www.olx.pl/d/oferta/pokoj-dwuosobowy-lublin-ul-paganiniego-czechow-blisko-um-kawalerka-CID3-ID19yGvY.html?search_reason=search%7Corganic",
      "address": "Paganiniego 12",
      "first_price": 1400,
      "current_price": 1300,
      "total_diff_pln": -100,
      "total_diff_pct": -7.14,
      "trend": "down",
      "first_seen": "2026-02-28T20:46:40.989752+01:00",
      "last_seen": "2026-03-08T15:57:36.798812+01:00",
      "active": false,
      "num_changes": 2,
      "has_coords": true,
      "timeline": [
        {
          "date": "2026-02-28T20:46:40.989752+01:00",
          "price": 1400,
          "approximated": false
        },
        {
          "date": "2026-03-01T15:58:00.861446+01:00",
          "price": 1300,
          "approximated": false
        }
      ]
    },
    {
      "id": "wynajme-pokoj-jednosobowy-na-ul-pana-balcera-CID3-ID19b3jV",
      "url": "https://www.olx.pl/d/oferta/wynajme-pokoj-jednosobowy-na-ul-pana-balcera-CID3-ID19b3jV.html?search_reason=search%7Cpromoted",
      "address": "Pana Balcera 1",
      "first_price": 900,
      "current_price": 800,
      "total_diff_pln": -100,
      "total_diff_pct": -11.11,
      "trend": "down",
      "first_seen": "2026-02-28T20:46:43.307512+01:00",
      "last_seen": "2026-03-29T10:37:57.938861+02:00",
      "active": false,
      "num_changes": 3,
      "has_coords": true,
      "timeline": [
        {
          "date": "2026-02-28T20:46:43.307512+01:00",
          "price": 900,
          "approximated": false
        },
        {
          "date": "2026-03-13T21:10:36.572034+01:00",
          "price": 880,
          "approximated": true
        },
        {
          "date": "2026-03-26T21:34:29.836556+01:00",
          "price": 800,
          "approximated": false
        }
      ]
    },
    {
      "id": "wynajme-pokoj-mieszkanie-stancje-CID3-ID14dmoV",
      "url": "https://www.olx.pl/d/oferta/wynajme-pokoj-mieszkanie-stancje-CID3-ID14dmoV.html?search_reason=search%7Corganic",
      "address": "Paganiniego 9",
      "first_price": 799,
      "current_price": 699,
      "total_diff_pln": -100,
      "total_diff_pct": -12.52,
      "trend": "down",
      "first_seen": "2026-02-28T20:46:43.329243+01:00",
      "last_seen": "2026-05-29T12:39:00.125261+02:00",
      "active": true,
      "num_changes": 2,
      "has_coords": true,
      "timeline": [
        {
          "date": "2026-02-28T20:46:43.329243+01:00",
          "price": 799,
          "approximated": false
        },
        {
          "date": "2026-05-08T22:08:27.685458+02:00",
          "price": 699,
          "approximated": false
        }
      ]
    },
    {
      "id": "do-wynajecia-pokoj-ul-gleboka-CID3-ID18Wz4T",
      "url": "https://www.olx.pl/d/oferta/do-wynajecia-pokoj-ul-gleboka-CID3-ID18Wz4T.html?search_reason=search%7Corganic",
      "address": "Głęboka 8",
      "first_price": 650,
      "current_price": 550,
      "total_diff_pln": -100,
      "total_diff_pct": -15.38,
      "trend": "down",
      "first_seen": "2026-03-01T11:26:07.349010+01:00",
      "last_seen": "2026-05-13T08:50:42.424793+02:00",
      "active": false,
      "num_changes": 2,
      "has_coords": true,
      "timeline": [
        {
          "date": "2026-03-01T11:26:07.349010+01:00",
          "price": 650,
          "approximated": false
        },
        {
          "date": "2026-04-02T10:53:13.050460+02:00",
          "price": 550,
          "approximated": false
        }
      ]
    },
    {
      "id": "pokoj-jednosobowy-pana-balcera-1-CID3-ID16Rf34",
      "url": "https://www.olx.pl/d/oferta/pokoj-jednosobowy-pana-balcera-1-CID3-ID16Rf34.html?search_reason=search%7Corganic",
      "address": "Pana Balcera 1",
      "first_price": 850,
      "current_price": 750,
      "total_diff_pln": -100,
      "total_diff_pct": -11.76,
      "trend": "down",
      "first_seen": "2026-03-01T11:26:12.466871+01:00",
      "last_seen": "2026-03-29T10:37:57.938861+02:00",
      "active": false,
      "num_changes": 3,
      "has_coords": true,
      "timeline": [
        {
          "date": "2026-03-01T11:26:12.466871+01:00",
          "price": 850,
          "approximated": false
        },
        {
          "date": "2026-03-14T04:30:21.151809+01:00",
          "price": 790,
          "approximated": true
        },
        {
          "date": "2026-03-26T21:34:29.836746+01:00",
          "price": 750,
          "approximated": false
        }
      ]
    },
    {
      "id": "pokoj-obok-uniwersytetu-medycznego-lublin-CID3-ID18CHWA",
      "url": "https://www.olx.pl/d/oferta/pokoj-obok-uniwersytetu-medycznego-lublin-CID3-ID18CHWA.html?search_reason=search%7Corganic",
      "address": "Ignacego Czumy 28W",
      "first_price": 1200,
      "current_price": 1100,
      "total_diff_pln": -100,
      "total_diff_pct": -8.33,
      "trend": "down",
      "first_seen": "2026-03-01T11:33:26.480766+01:00",
      "last_seen": "2026-05-29T12:39:00.125261+02:00",
      "active": true,
      "num_changes": 2,
      "has_coords": true,
      "timeline": [
        {
          "date": "2026-03-01T11:33:26.480766+01:00",
          "price": 1200,
          "approximated": false
        },
        {
          "date": "2026-03-01T15:58:00.861781+01:00",
          "price": 1100,
          "approximated": false
        }
      ]
    },
    {
      "id": "pokoj-1-osobowy-lsm-ul-rzeckiego-CID3-ID18aEFz",
      "url": "https://www.olx.pl/d/oferta/pokoj-1-osobowy-lsm-ul-rzeckiego-CID3-ID18aEFz.html?search_reason=search%7Corganic",
      "address": "Rzeckiego 4",
      "first_price": 1000,
      "current_price": 900,
      "total_diff_pln": -100,
      "total_diff_pct": -10.0,
      "trend": "down",
      "first_seen": "2026-03-01T15:57:54.018587+01:00",
      "last_seen": "2026-05-29T12:39:00.125261+02:00",
      "active": true,
      "num_changes": 2,
      "has_coords": true,
      "timeline": [
        {
          "date": "2026-03-01T15:57:54.018587+01:00",
          "price": 1000,
          "approximated": false
        },
        {
          "date": "2026-05-20T12:19:18.604924+02:00",
          "price": 900,
          "approximated": false
        }
      ]
    },
    {
      "id": "komfortowy-pokoj-1-osobowy-w-dobrej-lokalizacji-CID3-ID19FFgW",
      "url": "https://www.olx.pl/d/oferta/komfortowy-pokoj-1-osobowy-w-dobrej-lokalizacji-CID3-ID19FFgW.html?search_reason=search%7Corganic",
      "address": "Paganiniego 7",
      "first_price": 950,
      "current_price": 850,
      "total_diff_pln": -100,
      "total_diff_pct": -10.53,
      "trend": "down",
      "first_seen": "2026-03-06T17:00:02.271658+01:00",
      "last_seen": "2026-05-29T12:39:00.125261+02:00",
      "active": true,
      "num_changes": 2,
      "has_coords": true,
      "timeline": [
        {
          "date": "2026-03-06T17:00:02.271658+01:00",
          "price": 950,
          "approximated": false
        },
        {
          "date": "2026-03-15T21:25:03.669182+01:00",
          "price": 850,
          "approximated": false
        }
      ]
    },
    {
      "id": "pokoj-jednosobowy-lub-dwuosobowy-z-balkonem-czechow-kiepury-od-zaraz-CID3-ID18LQS6",
      "url": "https://www.olx.pl/d/oferta/pokoj-jednosobowy-lub-dwuosobowy-z-balkonem-czechow-kiepury-od-zaraz-CID3-ID18LQS6.html?search_reason=search%7Corganic",
      "address": "Kiepury 11",
      "first_price": 1100,
      "current_price": 1000,
      "total_diff_pln": -100,
      "total_diff_pct": -9.09,
      "trend": "down",
      "first_seen": "2026-03-09T11:35:02.726820+01:00",
      "last_seen": "2026-03-26T21:34:29.836979+01:00",
      "active": false,
      "num_changes": 2,
      "has_coords": true,
      "timeline": [
        {
          "date": "2026-03-09T11:35:02.726820+01:00",
          "price": 1100,
          "approximated": false
        },
        {
          "date": "2026-03-21T15:25:14.718728+01:00",
          "price": 1000,
          "approximated": false
        }
      ]
    },
    {
      "id": "pokoj-premium-uniwersytet-medyczny-nowe-mieszkanie-balkon-CID3-ID19HSA0",
      "url": "https://www.olx.pl/d/oferta/pokoj-premium-uniwersytet-medyczny-nowe-mieszkanie-balkon-CID3-ID19HSA0.html?search_reason=search%7Corganic",
      "address": "Biernackiego 17",
      "first_price": 1700,
      "current_price": 1600,
      "total_diff_pln": -100,
      "total_diff_pct": -5.88,
      "trend": "down",
      "first_seen": "2026-03-09T18:16:08.274122+01:00",
      "last_seen": "2026-04-08T10:57:59.230037+02:00",
      "active": false,
      "num_changes": 2,
      "has_coords": true,
      "timeline": [
        {
          "date": "2026-03-09T18:16:08.274122+01:00",
          "price": 1700,
          "approximated": false
        },
        {
          "date": "2026-03-27T15:48:42.547523+01:00",
          "price": 1600,
          "approximated": false
        }
      ]
    },
    {
      "id": "pokoj-w-promocji-grottgera-9-miasteczko-akademickie-bez-prowizji-CID3-ID19v2K1",
      "url": "https://www.olx.pl/d/oferta/pokoj-w-promocji-grottgera-9-miasteczko-akademickie-bez-prowizji-CID3-ID19v2K1.html?search_reason=search%7Corganic",
      "address": "Grottgera 9",
      "first_price": 870,
      "current_price": 770,
      "total_diff_pln": -100,
      "total_diff_pct": -11.49,
      "trend": "down",
      "first_seen": "2026-03-12T18:17:57.617919+01:00",
      "last_seen": "2026-04-24T11:00:24.436264+02:00",
      "active": false,
      "num_changes": 2,
      "has_coords": true,
      "timeline": [
        {
          "date": "2026-03-12T18:17:57.617919+01:00",
          "price": 870,
          "approximated": false
        },
        {
          "date": "2026-03-31T16:59:42.770029+02:00",
          "price": 770,
          "approximated": false
        }
      ]
    },
    {
      "id": "pokoj-ul-leszczynskiego-25-wolny-od-1-05-2025r-CID3-ID19WCI5",
      "url": "https://www.olx.pl/d/oferta/pokoj-ul-leszczynskiego-25-wolny-od-1-05-2025r-CID3-ID19WCI5.html?search_reason=search%7Corganic",
      "address": "Leszczyńskiego 25",
      "first_price": 1000,
      "current_price": 900,
      "total_diff_pln": -100,
      "total_diff_pct": -10.0,
      "trend": "down",
      "first_seen": "2026-03-24T15:57:08.676065+01:00",
      "last_seen": "2026-04-23T10:33:57.507910+02:00",
      "active": false,
      "num_changes": 2,
      "has_coords": true,
      "timeline": [
        {
          "date": "2026-03-24T15:57:08.676065+01:00",
          "price": 1000,
          "approximated": false
        },
        {
          "date": "2026-03-31T16:59:42.769478+02:00",
          "price": 900,
          "approximated": false
        }
      ]
    },
    {
      "id": "pokoj-do-wynajecia-bez-dodatkowych-oplat-CID3-IDYZij3",
      "url": "https://www.olx.pl/d/oferta/pokoj-do-wynajecia-bez-dodatkowych-oplat-CID3-IDYZij3.html?search_reason=search%7Cpromoted",
      "address": "Romera 6",
      "first_price": 1300,
      "current_price": 1200,
      "total_diff_pln": -100,
      "total_diff_pct": -7.69,
      "trend": "down",
      "first_seen": "2026-04-15T17:05:12.011625+02:00",
      "last_seen": "2026-05-08T16:35:31.251405+02:00",
      "active": false,
      "num_changes": 2,
      "has_coords": true,
      "timeline": [
        {
          "date": "2026-04-15T17:05:12.011625+02:00",
          "price": 1300,
          "approximated": false
        },
        {
          "date": "2026-04-18T10:45:00.435121+02:00",
          "price": 1200,
          "approximated": false
        }
      ]
    },
    {
      "id": "wynajme-pokoj-lublin-wrotkow-CID3-ID1ag7P4",
      "url": "https://www.olx.pl/d/oferta/wynajme-pokoj-lublin-wrotkow-CID3-ID1ag7P4.html?search_reason=search%7Corganic",
      "address": "Medalionów 2",
      "first_price": 1100,
      "current_price": 1000,
      "total_diff_pln": -100,
      "total_diff_pct": -9.09,
      "trend": "down",
      "first_seen": "2026-04-17T22:16:30.411593+02:00",
      "last_seen": "2026-05-17T16:22:25.054832+02:00",
      "active": false,
      "num_changes": 2,
      "has_coords": true,
      "timeline": [
        {
          "date": "2026-04-17T22:16:30.411593+02:00",
          "price": 1100,
          "approximated": false
        },
        {
          "date": "2026-05-10T10:53:14.623063+02:00",
          "price": 1000,
          "approximated": false
        }
      ]
    },
    {
      "id": "2-pokoje-do-wynajecia-1100zl-za-1-pokoj-brak-dodatkowych-oplat-os-choiny-CID3-ID16qGjk",
      "url": "https://www.olx.pl/d/oferta/2-pokoje-do-wynajecia-1100zl-za-1-pokoj-brak-dodatkowych-oplat-os-choiny-CID3-ID16qGjk.html?search_reason=search%7Corganic",
      "address": "Chodźki 4",
      "first_price": 1100,
      "current_price": 1000,
      "total_diff_pln": -100,
      "total_diff_pct": -9.09,
      "trend": "down",
      "first_seen": "2026-04-29T19:21:02.800059+02:00",
      "last_seen": "2026-05-23T22:01:58.707168+02:00",
      "active": false,
      "num_changes": 2,
      "has_coords": true,
      "timeline": [
        {
          "date": "2026-04-29T19:21:02.800059+02:00",
          "price": 1100,
          "approximated": false
        },
        {
          "date": "2026-04-30T11:11:56.869949+02:00",
          "price": 1000,
          "approximated": false
        }
      ]
    },
    {
      "id": "wynajme-pokoj-jednoosobowy-CID3-ID1ar9NS",
      "url": "https://www.olx.pl/d/oferta/wynajme-pokoj-jednoosobowy-CID3-ID1ar9NS.html?search_reason=search%7Corganic",
      "address": "Nowy Świat 5d",
      "first_price": 900,
      "current_price": 800,
      "total_diff_pln": -100,
      "total_diff_pct": -11.11,
      "trend": "down",
      "first_seen": "2026-04-30T17:04:34.438982+02:00",
      "last_seen": "2026-05-29T12:39:00.125261+02:00",
      "active": true,
      "num_changes": 2,
      "has_coords": true,
      "timeline": [
        {
          "date": "2026-04-30T17:04:34.438982+02:00",
          "price": 900,
          "approximated": false
        },
        {
          "date": "2026-05-10T16:21:28.246128+02:00",
          "price": 800,
          "approximated": false
        }
      ]
    },
    {
      "id": "jednoosobowy-pokoj-do-wynajecia-CID3-ID16mOEd",
      "url": "https://www.olx.pl/d/oferta/jednoosobowy-pokoj-do-wynajecia-CID3-ID16mOEd.html?search_reason=search%7Corganic",
      "address": "Żarnowiecka",
      "first_price": 950,
      "current_price": 850,
      "total_diff_pln": -100,
      "total_diff_pct": -10.53,
      "trend": "down",
      "first_seen": "2026-05-13T20:05:34.505135+02:00",
      "last_seen": "2026-05-28T23:03:09.824062+02:00",
      "active": false,
      "num_changes": 3,
      "has_coords": true,
      "timeline": [
        {
          "date": "2026-05-13T20:05:34.505135+02:00",
          "price": 950,
          "approximated": false
        },
        {
          "date": "2026-05-27T12:32:36.672496+02:00",
          "price": 900,
          "approximated": false
        },
        {
          "date": "2026-05-28T23:03:09.824062+02:00",
          "price": 850,
          "approximated": false
        }
      ]
    },
    {
      "id": "duzy-pokoj-z-balkonem-blisko-uczelni-i-centrum-CID3-ID19OLvV",
      "url": "https://www.olx.pl/d/oferta/duzy-pokoj-z-balkonem-blisko-uczelni-i-centrum-CID3-ID19OLvV.html?search_reason=search%7Corganic",
      "address": "Koncertowa 9",
      "first_price": 1000,
      "current_price": 900,
      "total_diff_pln": -100,
      "total_diff_pct": -10.0,
      "trend": "down",
      "first_seen": "2026-05-15T08:08:03.242767+02:00",
      "last_seen": "2026-05-29T12:39:00.125261+02:00",
      "active": true,
      "num_changes": 2,
      "has_coords": true,
      "timeline": [
        {
          "date": "2026-05-15T08:08:03.242767+02:00",
          "price": 1000,
          "approximated": false
        },
        {
          "date": "2026-05-25T12:53:51.010579+02:00",
          "price": 900,
          "approximated": false
        }
      ]
    },
    {
      "id": "pokoj-tv-wysoki-standard-lsm-okolice-zana-krasnickiej-CID3-IDHWVci",
      "url": "https://www.olx.pl/d/oferta/pokoj-tv-wysoki-standard-lsm-okolice-zana-krasnickiej-CID3-IDHWVci.html?search_reason=search%7Corganic",
      "address": "Aleja Kraśnickich",
      "first_price": 890,
      "current_price": 790,
      "total_diff_pln": -100,
      "total_diff_pct": -11.24,
      "trend": "down",
      "first_seen": "2026-05-15T08:08:05.044957+02:00",
      "last_seen": "2026-05-26T22:51:16.402116+02:00",
      "active": false,
      "num_changes": 2,
      "has_coords": true,
      "timeline": [
        {
          "date": "2026-05-15T08:08:05.044957+02:00",
          "price": 890,
          "approximated": false
        },
        {
          "date": "2026-05-20T12:19:18.602019+02:00",
          "price": 790,
          "approximated": false
        }
      ]
    },
    {
      "id": "centrum-pokoj-w-mieszkaniu-studenckim-CID3-ID1aITLd",
      "url": "https://www.olx.pl/d/oferta/centrum-pokoj-w-mieszkaniu-studenckim-CID3-ID1aITLd.html?search_reason=search%7Corganic",
      "address": "Narutowicza 65",
      "first_price": 1100,
      "current_price": 1000,
      "total_diff_pln": -100,
      "total_diff_pct": -9.09,
      "trend": "down",
      "first_seen": "2026-05-20T12:19:16.428881+02:00",
      "last_seen": "2026-05-29T12:39:00.123302+02:00",
      "active": true,
      "num_changes": 2,
      "has_coords": true,
      "timeline": [
        {
          "date": "2026-05-20T12:19:16.428861+02:00",
          "price": 1100,
          "approximated": false
        },
        {
          "date": "2026-05-29T12:39:00.123302+02:00",
          "price": 1000,
          "approximated": false
        }
      ]
    },
    {
      "id": "pokoj-1os-centrum-saski-od-lipca-w-m4-CID3-IDKcbzw",
      "url": "https://www.olx.pl/d/oferta/pokoj-1os-centrum-saski-od-lipca-w-m4-CID3-IDKcbzw.html?search_reason=search%7Cpromoted",
      "address": "Boczna Lubomelskiej",
      "first_price": 1000,
      "current_price": 900,
      "total_diff_pln": -100,
      "total_diff_pct": -10.0,
      "trend": "down",
      "first_seen": "2026-05-28T18:47:10.345062+02:00",
      "last_seen": "2026-05-29T12:39:00.115688+02:00",
      "active": true,
      "num_changes": 2,
      "has_coords": true,
      "timeline": [
        {
          "date": "2026-05-28T18:47:10.345051+02:00",
          "price": 1000,
          "approximated": false
        },
        {
          "date": "2026-05-29T12:39:00.110566+02:00",
          "price": 900,
          "approximated": false
        }
      ]
    },
    {
      "id": "pokoj-blisko-gorek-czechowskich-z-wifi-kiepury-11-bez-prowizji-CID3-ID18ptX9",
      "url": "https://www.olx.pl/d/oferta/pokoj-blisko-gorek-czechowskich-z-wifi-kiepury-11-bez-prowizji-CID3-ID18ptX9.html?search_reason=search%7Corganic",
      "address": "Kiepury 11",
      "first_price": 460,
      "current_price": 400,
      "total_diff_pln": -60,
      "total_diff_pct": -13.04,
      "trend": "down",
      "first_seen": "2026-03-27T15:48:42.331836+01:00",
      "last_seen": "2026-04-23T10:33:57.508582+02:00",
      "active": false,
      "num_changes": 2,
      "has_coords": true,
      "timeline": [
        {
          "date": "2026-03-27T15:48:42.331836+01:00",
          "price": 460,
          "approximated": false
        },
        {
          "date": "2026-03-31T16:59:42.769861+02:00",
          "price": 400,
          "approximated": false
        }
      ]
    },
    {
      "id": "pokoj-do-wynajecia-ul-mlodziezowa-CID3-ID173hD1",
      "url": "https://www.olx.pl/d/oferta/pokoj-do-wynajecia-ul-mlodziezowa-CID3-ID173hD1.html?search_reason=search%7Corganic",
      "address": "Młodzieżowa 9",
      "first_price": 850,
      "current_price": 800,
      "total_diff_pln": -50,
      "total_diff_pct": -5.88,
      "trend": "down",
      "first_seen": "2026-03-01T11:26:07.223249+01:00",
      "last_seen": "2026-05-20T12:19:18.608178+02:00",
      "active": false,
      "num_changes": 2,
      "has_coords": true,
      "timeline": [
        {
          "date": "2026-03-01T11:26:07.223249+01:00",
          "price": 850,
          "approximated": false
        },
        {
          "date": "2026-05-08T10:22:55.201940+02:00",
          "price": 800,
          "approximated": false
        }
      ]
    },
    {
      "id": "pokoj-jednoosobowy-od-zaraz-pana-balcera-1-lsm-blisko-centrum-CID3-ID15mH1J",
      "url": "https://www.olx.pl/d/oferta/pokoj-jednoosobowy-od-zaraz-pana-balcera-1-lsm-blisko-centrum-CID3-ID15mH1J.html?search_reason=search%7Corganic",
      "address": "Pana Balcera 1",
      "first_price": 850,
      "current_price": 800,
      "total_diff_pln": -50,
      "total_diff_pct": -5.88,
      "trend": "down",
      "first_seen": "2026-03-01T11:26:09.479634+01:00",
      "last_seen": "2026-03-29T16:33:15.200206+02:00",
      "active": false,
      "num_changes": 2,
      "has_coords": true,
      "timeline": [
        {
          "date": "2026-03-01T11:26:09.479634+01:00",
          "price": 850,
          "approximated": false
        },
        {
          "date": "2026-03-13T11:03:42.013707+01:00",
          "price": 800,
          "approximated": false
        }
      ]
    },
    {
      "id": "pokoj-na-wynajem-w-lublinie-11-m-blisko-uczelni-umeblowany-CID3-ID17hyT7",
      "url": "https://www.olx.pl/d/oferta/pokoj-na-wynajem-w-lublinie-11-m-blisko-uczelni-umeblowany-CID3-ID17hyT7.html?search_reason=search%7Corganic",
      "address": "Młodej Polski 02",
      "first_price": 700,
      "current_price": 650,
      "total_diff_pln": -50,
      "total_diff_pct": -7.14,
      "trend": "down",
      "first_seen": "2026-03-01T11:33:26.508677+01:00",
      "last_seen": "2026-05-23T22:01:58.707168+02:00",
      "active": false,
      "num_changes": 2,
      "has_coords": true,
      "timeline": [
        {
          "date": "2026-03-01T11:33:26.508677+01:00",
          "price": 700,
          "approximated": false
        },
        {
          "date": "2026-04-29T19:22:16.519525+02:00",
          "price": 650,
          "approximated": false
        }
      ]
    },
    {
      "id": "pokoj-w-mieszkaniu-studenckim-CID3-ID18KwMp",
      "url": "https://www.olx.pl/d/oferta/pokoj-w-mieszkaniu-studenckim-CID3-ID18KwMp.html?search_reason=search%7Corganic",
      "address": "Wołodyjowskiego 9",
      "first_price": 825,
      "current_price": 775,
      "total_diff_pln": -50,
      "total_diff_pct": -6.06,
      "trend": "down",
      "first_seen": "2026-03-01T15:57:56.435622+01:00",
      "last_seen": "2026-04-16T11:14:56.695063+02:00",
      "active": false,
      "num_changes": 2,
      "has_coords": true,
      "timeline": [
        {
          "date": "2026-03-01T15:57:56.435622+01:00",
          "price": 825,
          "approximated": false
        },
        {
          "date": "2026-03-18T16:02:31.400184+01:00",
          "price": 775,
          "approximated": false
        }
      ]
    },
    {
      "id": "przytulny-pokoj-do-wynajecia-blisko-politechnika-umcs-kul-CID3-ID19KCGG",
      "url": "https://www.olx.pl/d/oferta/przytulny-pokoj-do-wynajecia-blisko-politechnika-umcs-kul-CID3-ID19KCGG.html?search_reason=search%7Cpromoted",
      "address": "Emancypantek 3",
      "first_price": 850,
      "current_price": 800,
      "total_diff_pln": -50,
      "total_diff_pct": -5.88,
      "trend": "down",
      "first_seen": "2026-03-12T11:12:09.933503+01:00",
      "last_seen": "2026-04-11T10:39:04.887479+02:00",
      "active": false,
      "num_changes": 2,
      "has_coords": true,
      "timeline": [
        {
          "date": "2026-03-12T11:12:09.933503+01:00",
          "price": 850,
          "approximated": false
        },
        {
          "date": "2026-03-16T15:59:22.534843+01:00",
          "price": 800,
          "approximated": false
        }
      ]
    },
    {
      "id": "lsm-rury-pokoj-ul-chrobrego-CID3-ID19Tidc",
      "url": "https://www.olx.pl/d/oferta/lsm-rury-pokoj-ul-chrobrego-CID3-ID19Tidc.html?search_reason=search%7Corganic",
      "address": "Chrobrego 20",
      "first_price": 800,
      "current_price": 750,
      "total_diff_pln": -50,
      "total_diff_pct": -6.25,
      "trend": "down",
      "first_seen": "2026-03-21T21:23:17.314471+01:00",
      "last_seen": "2026-04-04T16:32:54.958441+02:00",
      "active": false,
      "num_changes": 2,
      "has_coords": true,
      "timeline": [
        {
          "date": "2026-03-21T21:23:17.314471+01:00",
          "price": 800,
          "approximated": false
        },
        {
          "date": "2026-03-27T15:48:42.547629+01:00",
          "price": 750,
          "approximated": false
        }
      ]
    },
    {
      "id": "duzy-pokoj-z-balkonem-ul-organowa-1-lublin-CID3-ID19hZeu",
      "url": "https://www.olx.pl/d/oferta/duzy-pokoj-z-balkonem-ul-organowa-1-lublin-CID3-ID19hZeu.html?search_reason=search%7Corganic",
      "address": "Organowa 1",
      "first_price": 1100,
      "current_price": 1050,
      "total_diff_pln": -50,
      "total_diff_pct": -4.55,
      "trend": "down",
      "first_seen": "2026-03-21T21:23:17.322475+01:00",
      "last_seen": "2026-05-23T22:01:58.707168+02:00",
      "active": false,
      "num_changes": 2,
      "has_coords": true,
      "timeline": [
        {
          "date": "2026-03-21T21:23:17.322475+01:00",
          "price": 1100,
          "approximated": false
        },
        {
          "date": "2026-04-27T17:02:28.540615+02:00",
          "price": 1050,
          "approximated": false
        }
      ]
    },
    {
      "id": "pokoj-jednoosobowy-jedynka-wieniawska-centrum-lublina-CID3-ID19q9Iw",
      "url": "https://www.olx.pl/d/oferta/pokoj-jednoosobowy-jedynka-wieniawska-centrum-lublina-CID3-ID19q9Iw.html?search_reason=search%7Corganic",
      "address": "Wieniawska 10",
      "first_price": 900,
      "current_price": 850,
      "total_diff_pln": -50,
      "total_diff_pct": -5.56,
      "trend": "down",
      "first_seen": "2026-04-24T11:00:24.150266+02:00",
      "last_seen": "2026-05-29T12:39:00.125261+02:00",
      "active": true,
      "num_changes": 2,
      "has_coords": true,
      "timeline": [
        {
          "date": "2026-04-24T11:00:24.150266+02:00",
          "price": 900,
          "approximated": false
        },
        {
          "date": "2026-04-24T16:32:58.563995+02:00",
          "price": 850,
          "approximated": false
        }
      ]
    },
    {
      "id": "wynajme-pokoj-jednoosobowy-ul-skierki-1-CID3-ID1awKDp",
      "url": "https://www.olx.pl/d/oferta/wynajme-pokoj-jednoosobowy-ul-skierki-1-CID3-ID1awKDp.html?search_reason=search%7Corganic",
      "address": "Skierki 1",
      "first_price": 800,
      "current_price": 750,
      "total_diff_pln": -50,
      "total_diff_pct": -6.25,
      "trend": "down",
      "first_seen": "2026-05-06T22:21:27.520467+02:00",
      "last_seen": "2026-05-29T12:39:00.125261+02:00",
      "active": true,
      "num_changes": 2,
      "has_coords": true,
      "timeline": [
        {
          "date": "2026-05-06T22:21:27.520467+02:00",
          "price": 800,
          "approximated": false
        },
        {
          "date": "2026-05-09T16:16:49.570003+02:00",
          "price": 750,
          "approximated": false
        }
      ]
    },
    {
      "id": "wynajme-pokoje-lsm-CID3-ID17pN4e",
      "url": "https://www.olx.pl/d/oferta/wynajme-pokoje-lsm-CID3-ID17pN4e.html?search_reason=search%7Corganic",
      "address": "Balladyny",
      "first_price": 950,
      "current_price": 900,
      "total_diff_pln": -50,
      "total_diff_pct": -5.26,
      "trend": "down",
      "first_seen": "2026-05-11T17:57:02.866062+02:00",
      "last_seen": "2026-05-15T11:39:57.957617+02:00",
      "active": false,
      "num_changes": 2,
      "has_coords": true,
      "timeline": [
        {
          "date": "2026-05-11T17:57:02.866062+02:00",
          "price": 950,
          "approximated": false
        },
        {
          "date": "2026-05-12T17:39:20.804101+02:00",
          "price": 900,
          "approximated": false
        }
      ]
    },
    {
      "id": "pokoj-marianska-blisko-uniwersytetu-medycznego-i-olimp-CID3-ID1arL6x",
      "url": "https://www.olx.pl/d/oferta/pokoj-marianska-blisko-uniwersytetu-medycznego-i-olimp-CID3-ID1arL6x.html?search_reason=search%7Corganic",
      "address": "Mariańskiej",
      "first_price": 1050,
      "current_price": 1000,
      "total_diff_pln": -50,
      "total_diff_pct": -4.76,
      "trend": "down",
      "first_seen": "2026-05-13T22:27:12.074582+02:00",
      "last_seen": "2026-05-26T18:36:57.479018+02:00",
      "active": false,
      "num_changes": 2,
      "has_coords": true,
      "timeline": [
        {
          "date": "2026-05-13T22:27:12.074582+02:00",
          "price": 1050,
          "approximated": false
        },
        {
          "date": "2026-05-19T12:32:41.960018+02:00",
          "price": 1000,
          "approximated": false
        }
      ]
    },
    {
      "id": "pokoj-1-osobowy-osiedle-slawin-bez-dodatkowych-oplat-CID3-ID1aDF28",
      "url": "https://www.olx.pl/d/oferta/pokoj-1-osobowy-osiedle-slawin-bez-dodatkowych-oplat-CID3-ID1aDF28.html?search_reason=search%7Cpromoted",
      "address": "Tulipanowej",
      "first_price": 950,
      "current_price": 900,
      "total_diff_pln": -50,
      "total_diff_pct": -5.26,
      "trend": "down",
      "first_seen": "2026-05-14T22:24:19.322229+02:00",
      "last_seen": "2026-05-29T12:39:00.125261+02:00",
      "active": true,
      "num_changes": 3,
      "has_coords": true,
      "timeline": [
        {
          "date": "2026-05-14T22:24:19.322229+02:00",
          "price": 950,
          "approximated": false
        },
        {
          "date": "2026-05-16T16:19:00.490844+02:00",
          "price": 920,
          "approximated": false
        },
        {
          "date": "2026-05-20T12:19:18.602869+02:00",
          "price": 900,
          "approximated": false
        }
      ]
    },
    {
      "id": "pokoj-do-wynajecia-dla-pani-lublin-ul-jesienna-blisko-felin-felicity-CID3-ID154GfK",
      "url": "https://www.olx.pl/d/oferta/pokoj-do-wynajecia-dla-pani-lublin-ul-jesienna-blisko-felin-felicity-CID3-ID154GfK.html?search_reason=search%7Corganic",
      "address": "Jesiennej",
      "first_price": 800,
      "current_price": 750,
      "total_diff_pln": -50,
      "total_diff_pct": -6.25,
      "trend": "down",
      "first_seen": "2026-05-15T22:10:23.787256+02:00",
      "last_seen": "2026-05-29T12:39:00.125261+02:00",
      "active": true,
      "num_changes": 2,
      "has_coords": true,
      "timeline": [
        {
          "date": "2026-05-15T22:10:23.787256+02:00",
          "price": 800,
          "approximated": false
        },
        {
          "date": "2026-05-22T15:05:11.377174+02:00",
          "price": 750,
          "approximated": false
        }
      ]
    },
    {
      "id": "pokoj-1-osobowy-ul-godebskiego-1-miasteczko-akademickie-CID3-ID1aKP2p",
      "url": "https://www.olx.pl/d/oferta/pokoj-1-osobowy-ul-godebskiego-1-miasteczko-akademickie-CID3-ID1aKP2p.html?search_reason=search%7Corganic",
      "address": "Godebskiego 1",
      "first_price": 1350,
      "current_price": 1300,
      "total_diff_pln": -50,
      "total_diff_pct": -3.7,
      "trend": "down",
      "first_seen": "2026-05-21T18:11:48.270126+02:00",
      "last_seen": "2026-05-29T12:39:00.125261+02:00",
      "active": true,
      "num_changes": 2,
      "has_coords": true,
      "timeline": [
        {
          "date": "2026-05-21T18:11:48.270117+02:00",
          "price": 1350,
          "approximated": false
        },
        {
          "date": "2026-05-22T10:45:22.339164+02:00",
          "price": 1300,
          "approximated": false
        }
      ]
    },
    {
      "id": "pokoj-dwuosobowy-prywatny-akademik-blisko-um-chodzki-13-CID3-IDVmiS7",
      "url": "https://www.olx.pl/d/oferta/pokoj-dwuosobowy-prywatny-akademik-blisko-um-chodzki-13-CID3-IDVmiS7.html?search_reason=search%7Corganic",
      "address": "Chodźki",
      "first_price": 1350,
      "current_price": 1300,
      "total_diff_pln": -50,
      "total_diff_pct": -3.7,
      "trend": "down",
      "first_seen": "2026-05-25T17:46:20.778296+02:00",
      "last_seen": "2026-05-29T12:39:00.125261+02:00",
      "active": true,
      "num_changes": 2,
      "has_coords": true,
      "timeline": [
        {
          "date": "2026-05-25T17:46:20.778281+02:00",
          "price": 1350,
          "approximated": false
        },
        {
          "date": "2026-05-28T12:45:32.499014+02:00",
          "price": 1300,
          "approximated": false
        }
      ]
    },
    {
      "id": "pokoj-do-wynajecia-studentki-stancja-dla-studentow-CID3-ID14JnMD",
      "url": "https://www.olx.pl/d/oferta/pokoj-do-wynajecia-studentki-stancja-dla-studentow-CID3-ID14JnMD.html?search_reason=search%7Corganic",
      "address": "Uniwersytetu Medycznego",
      "first_price": 850,
      "current_price": 800,
      "total_diff_pln": -50,
      "total_diff_pct": -5.88,
      "trend": "down",
      "first_seen": "2026-05-26T18:36:57.216818+02:00",
      "last_seen": "2026-05-29T12:39:00.125261+02:00",
      "active": true,
      "num_changes": 2,
      "has_coords": true,
      "timeline": [
        {
          "date": "2026-05-26T18:36:57.216802+02:00",
          "price": 850,
          "approximated": false
        },
        {
          "date": "2026-05-27T12:32:36.671300+02:00",
          "price": 800,
          "approximated": false
        }
      ]
    },
    {
      "id": "wolny-od-zaraz-super-lokalizacja-blisko-centrum-ul-paganiniego-12-CID3-ID195dLc",
      "url": "https://www.olx.pl/d/oferta/wolny-od-zaraz-super-lokalizacja-blisko-centrum-ul-paganiniego-12-CID3-ID195dLc.html?search_reason=search%7Corganic",
      "address": "Paganiniego 12",
      "first_price": 640,
      "current_price": 600,
      "total_diff_pln": -40,
      "total_diff_pct": -6.25,
      "trend": "down",
      "first_seen": "2026-02-28T20:46:43.291550+01:00",
      "last_seen": "2026-03-20T09:37:56.323506+01:00",
      "active": false,
      "num_changes": 2,
      "has_coords": true,
      "timeline": [
        {
          "date": "2026-02-28T20:46:43.291550+01:00",
          "price": 640,
          "approximated": false
        },
        {
          "date": "2026-03-10T18:13:00.796767+01:00",
          "price": 600,
          "approximated": false
        }
      ]
    },
    {
      "id": "wolny-od-zaraz-pokoj-jedynka-ul-romanowskiego-58-CID3-ID16ZeYm",
      "url": "https://www.olx.pl/d/oferta/wolny-od-zaraz-pokoj-jedynka-ul-romanowskiego-58-CID3-ID16ZeYm.html?search_reason=search%7Corganic",
      "address": "Romanowskiego 58",
      "first_price": 640,
      "current_price": 600,
      "total_diff_pln": -40,
      "total_diff_pct": -6.25,
      "trend": "down",
      "first_seen": "2026-02-28T20:46:43.294954+01:00",
      "last_seen": "2026-05-29T12:39:00.125261+02:00",
      "active": true,
      "num_changes": 2,
      "has_coords": true,
      "timeline": [
        {
          "date": "2026-02-28T20:46:43.294954+01:00",
          "price": 640,
          "approximated": false
        },
        {
          "date": "2026-03-10T18:13:00.796796+01:00",
          "price": 600,
          "approximated": false
        }
      ]
    },
    {
      "id": "uroczy-pokoj-dla-osoby-pracujacej-w-bloku-na-parterze-ul-lotnicza-4-CID3-IDVwpy4",
      "url": "https://www.olx.pl/d/oferta/uroczy-pokoj-dla-osoby-pracujacej-w-bloku-na-parterze-ul-lotnicza-4-CID3-IDVwpy4.html?search_reason=search%7Corganic",
      "address": "Lotnicza 4",
      "first_price": 720,
      "current_price": 680,
      "total_diff_pln": -40,
      "total_diff_pct": -5.56,
      "trend": "down",
      "first_seen": "2026-04-29T19:21:35.507770+02:00",
      "last_seen": "2026-05-29T12:39:00.125261+02:00",
      "active": true,
      "num_changes": 2,
      "has_coords": true,
      "timeline": [
        {
          "date": "2026-04-29T19:21:35.507770+02:00",
          "price": 720,
          "approximated": false
        },
        {
          "date": "2026-05-07T17:30:04.527623+02:00",
          "price": 680,
          "approximated": false
        }
      ]
    },
    {
      "id": "ladny-pokoj-jednoosobowy-wynajme-duzy-pokoj-w-centrum-ul-niecala-4-CID3-ID122jPM",
      "url": "https://www.olx.pl/d/oferta/ladny-pokoj-jednoosobowy-wynajme-duzy-pokoj-w-centrum-ul-niecala-4-CID3-ID122jPM.html?search_reason=search%7Corganic",
      "address": "Niecała 4",
      "first_price": 730,
      "current_price": 710,
      "total_diff_pln": -20,
      "total_diff_pct": -2.74,
      "trend": "down",
      "first_seen": "2026-02-28T20:46:41.004494+01:00",
      "last_seen": "2026-05-18T12:58:42.303320+02:00",
      "active": false,
      "num_changes": 2,
      "has_coords": true,
      "timeline": [
        {
          "date": "2026-02-28T20:46:41.004494+01:00",
          "price": 730,
          "approximated": false
        },
        {
          "date": "2026-05-07T17:30:04.527529+02:00",
          "price": 710,
          "approximated": false
        }
      ]
    },
    {
      "id": "2-pokoje-w-mieszkaniu-CID3-ID18HkLj",
      "url": "https://www.olx.pl/d/oferta/2-pokoje-w-mieszkaniu-CID3-ID18HkLj.html?search_reason=search%7Corganic",
      "address": "Czechów",
      "first_price": 1450,
      "current_price": 1445,
      "total_diff_pln": -5,
      "total_diff_pct": -0.34,
      "trend": "down",
      "first_seen": "2026-05-26T22:02:28.080607+02:00",
      "last_seen": "2026-05-29T12:39:00.125261+02:00",
      "active": true,
      "num_changes": 2,
      "has_coords": true,
      "timeline": [
        {
          "date": "2026-05-26T22:02:28.080595+02:00",
          "price": 1450,
          "approximated": false
        },
        {
          "date": "2026-05-27T12:32:36.673237+02:00",
          "price": 1445,
          "approximated": false
        }
      ]
    },
    {
      "id": "przytulny-pokoj-blisko-politechniki-ul-przytulna-CID3-ID17NeTz",
      "url": "https://www.olx.pl/d/oferta/przytulny-pokoj-blisko-politechniki-ul-przytulna-CID3-ID17NeTz.html?search_reason=search%7Cpromoted",
      "address": "Przytulna 6A",
      "first_price": 550,
      "current_price": 549,
      "total_diff_pln": -1,
      "total_diff_pct": -0.18,
      "trend": "down",
      "first_seen": "2026-02-28T20:46:42.759843+01:00",
      "last_seen": "2026-04-10T11:04:59.229966+02:00",
      "active": false,
      "num_changes": 2,
      "has_coords": true,
      "timeline": [
        {
          "date": "2026-02-28T20:46:42.759843+01:00",
          "price": 550,
          "approximated": false
        },
        {
          "date": "2026-03-01T15:58:00.861535+01:00",
          "price": 549,
          "approximated": false
        }
      ]
    },
    {
      "id": "wynajme-pokoj-lsm-wallenroda-CID3-ID1awhGk",
      "url": "https://www.olx.pl/d/oferta/wynajme-pokoj-lsm-wallenroda-CID3-ID1awhGk.html?search_reason=search%7Corganic",
      "address": "Wallenroda",
      "first_price": 690,
      "current_price": 700,
      "total_diff_pln": 10,
      "total_diff_pct": 1.45,
      "trend": "up",
      "first_seen": "2026-05-15T08:08:08.488538+02:00",
      "last_seen": "2026-05-29T12:39:00.125261+02:00",
      "active": true,
      "num_changes": 4,
      "has_coords": true,
      "timeline": [
        {
          "date": "2026-05-15T08:08:08.488538+02:00",
          "price": 690,
          "approximated": false
        },
        {
          "date": "2026-05-20T12:19:18.604462+02:00",
          "price": 700,
          "approximated": false
        },
        {
          "date": "2026-05-25T12:53:51.011977+02:00",
          "price": 690,
          "approximated": false
        },
        {
          "date": "2026-05-27T18:32:50.040501+02:00",
          "price": 700,
          "approximated": false
        }
      ]
    },
    {
      "id": "wybajme-pokoj-jednoosobowy-CID3-ID19mQPE",
      "url": "https://www.olx.pl/d/oferta/wybajme-pokoj-jednoosobowy-CID3-ID19mQPE.html?search_reason=search%7Corganic",
      "address": "Juranda 1",
      "first_price": 800,
      "current_price": 850,
      "total_diff_pln": 50,
      "total_diff_pct": 6.25,
      "trend": "up",
      "first_seen": "2026-02-28T20:46:41.009326+01:00",
      "last_seen": "2026-03-03T21:51:31.928897+01:00",
      "active": false,
      "num_changes": 2,
      "has_coords": true,
      "timeline": [
        {
          "date": "2026-02-28T20:46:41.009326+01:00",
          "price": 800,
          "approximated": false
        },
        {
          "date": "2026-03-01T15:58:00.861418+01:00",
          "price": 850,
          "approximated": false
        }
      ]
    },
    {
      "id": "pokoje-do-wynajecia-lsm-ul-jana-sawy-CID3-ID13IhQI",
      "url": "https://www.olx.pl/d/oferta/pokoje-do-wynajecia-lsm-ul-jana-sawy-CID3-ID13IhQI.html?search_reason=search%7Cpromoted",
      "address": "Jana Sawy 15",
      "first_price": 750,
      "current_price": 800,
      "total_diff_pln": 50,
      "total_diff_pct": 6.67,
      "trend": "up",
      "first_seen": "2026-02-28T20:46:43.312679+01:00",
      "last_seen": "2026-05-29T12:39:00.125261+02:00",
      "active": true,
      "num_changes": 3,
      "has_coords": true,
      "timeline": [
        {
          "date": "2026-02-28T20:46:43.312679+01:00",
          "price": 750,
          "approximated": false
        },
        {
          "date": "2026-03-24T09:15:59.536244+01:00",
          "price": 700,
          "approximated": true
        },
        {
          "date": "2026-04-16T22:45:15.759809+02:00",
          "price": 800,
          "approximated": false
        }
      ]
    },
    {
      "id": "pokoj-z-balkonem-do-wynajecia-ul-organowa-1-lublin-CID3-ID19hZeu",
      "url": "https://www.olx.pl/d/oferta/pokoj-z-balkonem-do-wynajecia-ul-organowa-1-lublin-CID3-ID19hZeu.html?search_reason=search%7Corganic",
      "address": "Organowa 1",
      "first_price": 1000,
      "current_price": 1050,
      "total_diff_pln": 50,
      "total_diff_pct": 5.0,
      "trend": "up",
      "first_seen": "2026-05-07T17:30:04.024618+02:00",
      "last_seen": "2026-05-27T12:49:46.693510+02:00",
      "active": false,
      "num_changes": 2,
      "has_coords": true,
      "timeline": [
        {
          "date": "2026-05-07T17:30:04.024618+02:00",
          "price": 1000,
          "approximated": false
        },
        {
          "date": "2026-05-19T12:32:41.961008+02:00",
          "price": 1050,
          "approximated": false
        }
      ]
    },
    {
      "id": "pokoj-przy-uczelni-gleboka-p-tadeusza-12-pokoj-1-os-umcs-kul-up-CID3-ID13IDz0",
      "url": "https://www.olx.pl/d/oferta/pokoj-przy-uczelni-gleboka-p-tadeusza-12-pokoj-1-os-umcs-kul-up-CID3-ID13IDz0.html?search_reason=search%7Corganic",
      "address": "Pana Tadeusza",
      "first_price": 950,
      "current_price": 1000,
      "total_diff_pln": 50,
      "total_diff_pct": 5.26,
      "trend": "up",
      "first_seen": "2026-05-11T12:33:20.379638+02:00",
      "last_seen": "2026-05-29T12:39:00.125261+02:00",
      "active": true,
      "num_changes": 2,
      "has_coords": true,
      "timeline": [
        {
          "date": "2026-05-11T12:33:20.379638+02:00",
          "price": 950,
          "approximated": false
        },
        {
          "date": "2026-05-25T12:53:51.009225+02:00",
          "price": 1000,
          "approximated": false
        }
      ]
    },
    {
      "id": "pokoj-jednoosobowy-pogodna-CID3-ID1alxY8",
      "url": "https://www.olx.pl/d/oferta/pokoj-jednoosobowy-pogodna-CID3-ID1alxY8.html?search_reason=search%7Corganic",
      "address": "Pogodna",
      "first_price": 750,
      "current_price": 800,
      "total_diff_pln": 50,
      "total_diff_pct": 6.67,
      "trend": "up",
      "first_seen": "2026-05-13T22:07:01.769122+02:00",
      "last_seen": "2026-05-23T16:26:07.185495+02:00",
      "active": false,
      "num_changes": 2,
      "has_coords": true,
      "timeline": [
        {
          "date": "2026-05-13T22:07:01.769122+02:00",
          "price": 750,
          "approximated": false
        },
        {
          "date": "2026-05-23T16:26:07.185495+02:00",
          "price": 800,
          "approximated": false
        }
      ]
    },
    {
      "id": "pokoj-w-mieszkaniu-dwupokojowym-CID3-ID19PD8i",
      "url": "https://www.olx.pl/d/oferta/pokoj-w-mieszkaniu-dwupokojowym-CID3-ID19PD8i.html?search_reason=search%7Corganic",
      "address": "Rury",
      "first_price": 600,
      "current_price": 650,
      "total_diff_pln": 50,
      "total_diff_pct": 8.33,
      "trend": "up",
      "first_seen": "2026-05-28T18:47:10.298918+02:00",
      "last_seen": "2026-05-29T12:39:00.110819+02:00",
      "active": true,
      "num_changes": 2,
      "has_coords": true,
      "timeline": [
        {
          "date": "2026-05-28T18:47:10.298896+02:00",
          "price": 600,
          "approximated": false
        },
        {
          "date": "2026-05-29T12:39:00.110819+02:00",
          "price": 650,
          "approximated": false
        }
      ]
    },
    {
      "id": "pokoj-1-osobowy-w-centrum-lublina-wynajme-CID3-IDYrt7R",
      "url": "https://www.olx.pl/d/oferta/pokoj-1-osobowy-w-centrum-lublina-wynajme-CID3-IDYrt7R.html?search_reason=search%7Corganic",
      "address": "Śnieżyńskiego 10",
      "first_price": 690,
      "current_price": 750,
      "total_diff_pln": 60,
      "total_diff_pct": 8.7,
      "trend": "up",
      "first_seen": "2026-02-28T20:46:43.335699+01:00",
      "last_seen": "2026-05-11T22:30:09.243036+02:00",
      "active": false,
      "num_changes": 2,
      "has_coords": true,
      "timeline": [
        {
          "date": "2026-02-28T20:46:43.335699+01:00",
          "price": 690,
          "approximated": false
        },
        {
          "date": "2026-04-16T17:25:37.409793+02:00",
          "price": 750,
          "approximated": false
        }
      ]
    },
    {
      "id": "pokoj-zimowa-10-blisko-felicity-makro-park-nauk-t-leroy-CID3-ID16NwCl",
      "url": "https://www.olx.pl/d/oferta/pokoj-zimowa-10-blisko-felicity-makro-park-nauk-t-leroy-CID3-ID16NwCl.html?search_reason=search%7Corganic",
      "address": "Zimowa 10",
      "first_price": 780,
      "current_price": 850,
      "total_diff_pln": 70,
      "total_diff_pct": 8.97,
      "trend": "up",
      "first_seen": "2026-03-02T11:35:42.814321+01:00",
      "last_seen": "2026-05-29T12:39:00.125261+02:00",
      "active": true,
      "num_changes": 2,
      "has_coords": true,
      "timeline": [
        {
          "date": "2026-03-02T11:35:42.814321+01:00",
          "price": 780,
          "approximated": false
        },
        {
          "date": "2026-05-26T14:49:29.855990+02:00",
          "price": 850,
          "approximated": false
        }
      ]
    },
    {
      "id": "pokoj-z-balkonem-do-wynajecia-od-zaraz-lublin-ul-lwowska-18-CID3-ID19NTPE",
      "url": "https://www.olx.pl/d/oferta/pokoj-z-balkonem-do-wynajecia-od-zaraz-lublin-ul-lwowska-18-CID3-ID19NTPE.html?search_reason=search%7Corganic",
      "address": "Lwowska 18",
      "first_price": 730,
      "current_price": 800,
      "total_diff_pln": 70,
      "total_diff_pct": 9.59,
      "trend": "up",
      "first_seen": "2026-03-15T21:25:02.414626+01:00",
      "last_seen": "2026-04-02T10:53:13.051461+02:00",
      "active": false,
      "num_changes": 2,
      "has_coords": true,
      "timeline": [
        {
          "date": "2026-03-15T21:25:02.414626+01:00",
          "price": 730,
          "approximated": false
        },
        {
          "date": "2026-03-18T21:33:31.992364+01:00",
          "price": 800,
          "approximated": false
        }
      ]
    },
    {
      "id": "wynajme-pokoj-na-lsm-centrum-ul-pana-tadeusza-2-obok-gleboka-CID3-ID16PWHZ",
      "url": "https://www.olx.pl/d/oferta/wynajme-pokoj-na-lsm-centrum-ul-pana-tadeusza-2-obok-gleboka-CID3-ID16PWHZ.html?search_reason=search%7Corganic",
      "address": "Pana Tadeusza 2",
      "first_price": 900,
      "current_price": 1000,
      "total_diff_pln": 100,
      "total_diff_pct": 11.11,
      "trend": "up",
      "first_seen": "2026-03-01T11:33:27.009942+01:00",
      "last_seen": "2026-04-13T17:14:51.223097+02:00",
      "active": false,
      "num_changes": 2,
      "has_coords": true,
      "timeline": [
        {
          "date": "2026-03-01T11:33:27.009942+01:00",
          "price": 900,
          "approximated": false
        },
        {
          "date": "2026-03-14T21:24:14.536137+01:00",
          "price": 1000,
          "approximated": false
        }
      ]
    },
    {
      "id": "pokoj-jednosobowy-pana-balcera-1-CID3-ID1ad21V",
      "url": "https://www.olx.pl/d/oferta/pokoj-jednosobowy-pana-balcera-1-CID3-ID1ad21V.html?search_reason=search%7Corganic",
      "address": "Pana Balcera 1",
      "first_price": 800,
      "current_price": 900,
      "total_diff_pln": 100,
      "total_diff_pct": 12.5,
      "trend": "up",
      "first_seen": "2026-04-14T11:14:57.445074+02:00",
      "last_seen": "2026-05-29T12:39:00.125261+02:00",
      "active": true,
      "num_changes": 2,
      "has_coords": true,
      "timeline": [
        {
          "date": "2026-04-14T11:14:57.445074+02:00",
          "price": 800,
          "approximated": false
        },
        {
          "date": "2026-05-23T22:01:58.697539+02:00",
          "price": 900,
          "approximated": false
        }
      ]
    },
    {
      "id": "pokoj-duzy-do-wynajecia-blisko-politechniki-2-min-spacerem-CID3-ID16AWo3",
      "url": "https://www.olx.pl/d/oferta/pokoj-duzy-do-wynajecia-blisko-politechniki-2-min-spacerem-CID3-ID16AWo3.html?search_reason=search%7Corganic",
      "address": "Plażowa 12",
      "first_price": 1000,
      "current_price": 1200,
      "total_diff_pln": 200,
      "total_diff_pct": 20.0,
      "trend": "up",
      "first_seen": "2026-03-01T11:33:26.581649+01:00",
      "last_seen": "2026-03-20T09:37:56.323506+01:00",
      "active": false,
      "num_changes": 2,
      "has_coords": true,
      "timeline": [
        {
          "date": "2026-03-01T11:33:26.581649+01:00",
          "price": 1000,
          "approximated": false
        },
        {
          "date": "2026-03-04T17:05:35.369701+01:00",
          "price": 1200,
          "approximated": false
        }
      ]
    },
    {
      "id": "wynajme-mieszkanie-pokoje-w-centrum-lublina-okazja-CID3-ID18gz5K",
      "url": "https://www.olx.pl/d/oferta/wynajme-mieszkanie-pokoje-w-centrum-lublina-okazja-CID3-ID18gz5K.html?search_reason=search%7Corganic",
      "address": "Skrzatów 9",
      "first_price": 800,
      "current_price": 1000,
      "total_diff_pln": 200,
      "total_diff_pct": 25.0,
      "trend": "up",
      "first_seen": "2026-05-16T10:45:10.643661+02:00",
      "last_seen": "2026-05-29T12:39:00.125261+02:00",
      "active": true,
      "num_changes": 2,
      "has_coords": true,
      "timeline": [
        {
          "date": "2026-05-16T10:45:10.643661+02:00",
          "price": 800,
          "approximated": false
        },
        {
          "date": "2026-05-26T14:49:29.855539+02:00",
          "price": 1000,
          "approximated": false
        }
      ]
    },
    {
      "id": "pokoj-do-wynajecia-lublin-botanik-CID3-ID14X9Rx",
      "url": "https://www.olx.pl/d/oferta/pokoj-do-wynajecia-lublin-botanik-CID3-ID14X9Rx.html?search_reason=search%7Corganic",
      "address": "Poligonowa 8",
      "first_price": 800,
      "current_price": 1050,
      "total_diff_pln": 250,
      "total_diff_pct": 31.25,
      "trend": "up",
      "first_seen": "2026-03-01T11:33:26.545443+01:00",
      "last_seen": "2026-05-28T23:03:09.825424+02:00",
      "active": false,
      "num_changes": 2,
      "has_coords": true,
      "timeline": [
        {
          "date": "2026-03-01T11:33:26.545443+01:00",
          "price": 800,
          "approximated": false
        },
        {
          "date": "2026-04-26T10:16:55.766406+02:00",
          "price": 1050,
          "approximated": false
        }
      ]
    },
    {
      "id": "pokoj-jednoosobowy-bronowice-pogodna-CID3-ID1amWPY",
      "url": "https://www.olx.pl/d/oferta/pokoj-jednoosobowy-bronowice-pogodna-CID3-ID1amWPY.html?search_reason=search%7Corganic",
      "address": "Pogodnej",
      "first_price": 950,
      "current_price": 1200,
      "total_diff_pln": 250,
      "total_diff_pct": 26.32,
      "trend": "up",
      "first_seen": "2026-05-13T20:04:27.390981+02:00",
      "last_seen": "2026-05-25T13:30:13.626769+02:00",
      "active": false,
      "num_changes": 2,
      "has_coords": true,
      "timeline": [
        {
          "date": "2026-05-13T20:04:27.390981+02:00",
          "price": 950,
          "approximated": false
        },
        {
          "date": "2026-05-19T18:14:20.296190+02:00",
          "price": 1200,
          "approximated": false
        }
      ]
    },
    {
      "id": "komfortowy-pokoj-z-klimatyzacja-wolny-od-1-6-CID3-ID16WJZ7",
      "url": "https://www.olx.pl/d/oferta/komfortowy-pokoj-z-klimatyzacja-wolny-od-1-6-CID3-ID16WJZ7.html?search_reason=search%7Corganic",
      "address": "Koralowa 9",
      "first_price": 1000,
      "current_price": 1400,
      "total_diff_pln": 400,
      "total_diff_pct": 40.0,
      "trend": "up",
      "first_seen": "2026-05-14T08:02:50.712612+02:00",
      "last_seen": "2026-05-29T12:39:00.125261+02:00",
      "active": true,
      "num_changes": 2,
      "has_coords": true,
      "timeline": [
        {
          "date": "2026-05-14T08:02:50.712612+02:00",
          "price": 1000,
          "approximated": false
        },
        {
          "date": "2026-05-15T08:08:09.087050+02:00",
          "price": 1400,
          "approximated": false
        }
      ]
    },
    {
      "id": "wynajme-od-zaraz-pokoj-CID3-ID17pIVy",
      "url": "https://www.olx.pl/d/oferta/wynajme-od-zaraz-pokoj-CID3-ID17pIVy.html?search_reason=search%7Corganic",
      "address": "Rolna 2C",
      "first_price": 150,
      "current_price": 700,
      "total_diff_pln": 550,
      "total_diff_pct": 366.67,
      "trend": "up",
      "first_seen": "2026-03-01T15:57:59.507785+01:00",
      "last_seen": "2026-03-11T11:12:08.507694+01:00",
      "active": false,
      "num_changes": 2,
      "has_coords": true,
      "timeline": [
        {
          "date": "2026-03-01T15:57:59.507785+01:00",
          "price": 150,
          "approximated": false
        },
        {
          "date": "2026-03-01T20:18:35.707899+01:00",
          "price": 700,
          "approximated": false
        }
      ]
    },
    {
      "id": "pokoj-dla-studentow-po-remoncie-lublin-ul-nadbystrzycka-97-CID3-ID19AkNt",
      "url": "https://www.olx.pl/d/oferta/pokoj-dla-studentow-po-remoncie-lublin-ul-nadbystrzycka-97-CID3-ID19AkNt.html?search_reason=search%7Corganic",
      "address": "Nadbystrzycka 97",
      "first_price": 700,
      "current_price": 1300,
      "total_diff_pln": 600,
      "total_diff_pct": 85.71,
      "trend": "up",
      "first_seen": "2026-03-01T11:26:07.207863+01:00",
      "last_seen": "2026-03-30T22:42:33.211565+02:00",
      "active": false,
      "num_changes": 2,
      "has_coords": true,
      "timeline": [
        {
          "date": "2026-03-01T11:26:07.207863+01:00",
          "price": 700,
          "approximated": false
        },
        {
          "date": "2026-03-01T15:58:00.861454+01:00",
          "price": 1300,
          "approximated": false
        }
      ]
    }
  ]
}